deployer/__init__.py
deployer/application.py
deployer/executor.py
farfetch/__init__.py
farfetch/catalogs.py
farfetch/converter.py
farfetch/covers.py
farfetch/images.py
farfetch/keys.py
farfetch/network.py
farfetch/products.py
farfetch/repository.py
farfetch/task.py
farfetch/test.py
farfetch/trace_tools.py
farfetch/transmitter.py
intramirror/__init__.py
intramirror/catalog.py
intramirror/category.py
intramirror/dao.py
intramirror/download_images.py
intramirror/downloader.py
intramirror/executor.py
intramirror/product.py
intramirror/repository.py
intramirror/spider_products.py
intramirror/synchronizer.py
intramirror/task.py
intramirror/transmitter.py
intramirror/upload_aliyun.py
modules/__init__.py
modules/network/__init__.py
modules/network/network.py
modules/repository/__init__.py
modules/repository/repository.py
modules/scheduler/__init__.py
modules/scheduler/scheudler.py
modules/tools/__init__.py
modules/tools/common.py
modules/tools/translate.py
monitor/__init__.py
monitor/farfetch_monitor.py
monitor/intramirror_monitor.py
monitor/product_monitor.py
monitor/repository.py
mozia/__init__.py
mozia/crawler/__init__.py
mozia/crawler/application.py
mozia/crawler/catalog.py
mozia/crawler/downloader.py
mozia/crawler/manager.py
mozia/crawler/repository.py
mozia/crawler/monitor/__init__.py
mozia/crawler/monitor/monitor.py
mozia/crawler/proxy/__init__.py
mozia/crawler/proxy/farfetch.py
mozia/crawler/proxy/intramirror.py
mozia/crawler/proxy/resolver.py
mozia/crawler/tools/__init__.py
mozia/crawler/tools/ftp_client.py
mozia/crawler/tools/oss_utils.py
mozia/crawler/tools/repair_task_cover_url.py
mozia/crawler/tools/save_cover_to_ftp.py
mozia/crawler/tools/save_cover_to_oss.py
mozia/crawler/tools/set_product_cover.py
mozia/crawler/tools/task_cover_url.py
mozia_modules-1.8.3.dist-info/DESCRIPTION.rst
mozia_modules-1.8.3.dist-info/METADATA
mozia_modules-1.8.3.dist-info/RECORD
mozia_modules-1.8.3.dist-info/WHEEL
mozia_modules-1.8.3.dist-info/metadata.json
mozia_modules-1.8.3.dist-info/top_level.txt
