Metadata-Version: 1.1
Name: mozia-modules
Version: 1.8.3
Summary: Modules for mozia
Home-page: https://github.com/tangknives
Author: Joe Yuan
Author-email: tangknives@qq.com
License: MIT
Keywords: crawl,mysql,redis
Platform: UNKNOWN
Classifier: Development Status :: 4 - Beta
Classifier: Intended Audience :: Developers
Classifier: Topic :: Software Development :: Build Tools
Classifier: License :: OSI Approved :: MIT License
Classifier: Programming Language :: Python :: 2.6
Classifier: Programming Language :: Python :: 2.7
Classifier: Programming Language :: Python :: 3
Classifier: Programming Language :: Python :: 3.3
Classifier: Programming Language :: Python :: 3.4
Classifier: Programming Language :: Python :: 3.5
